MANIFEST.in
README.rst
setup.cfg
setup.py
shuyucms/__init__.py
shuyucms/__init__.pyc
shuyucms/__init__.py~
shuyucms/urls.py
shuyucms.egg-info/PKG-INFO
shuyucms.egg-info/SOURCES.txt
shuyucms.egg-info/dependency_links.txt
shuyucms.egg-info/entry_points.txt
shuyucms.egg-info/not-zip-safe
shuyucms.egg-info/requires.txt
shuyucms.egg-info/top_level.txt
shuyucms/.idea/jsLibraryMappings.xml
shuyucms/.idea/misc.xml
shuyucms/.idea/modules.xml
shuyucms/.idea/shuyucms.iml
shuyucms/.idea/workspace.xml
shuyucms/.idea/inspectionProfiles/Project_Default.xml
shuyucms/.idea/inspectionProfiles/profiles_settings.xml
shuyucms/bin/__init__.py
shuyucms/bin/shuyucms_project.py
shuyucms/boot/__init__.py
shuyucms/boot/lazy_admin.py
shuyucms/boot/models.py
shuyucms/boot/updates/contrib/admin/models.py
shuyucms/boot/updates/contrib/admin/util.py
shuyucms/boot/updates/contrib/admin/widgets.py
shuyucms/boot/updates/contrib/admin/templatetags/admin_list.py
shuyucms/boot/updates/contrib/auth/forms.py
shuyucms/boot/updates/contrib/auth/models.py
shuyucms/boot/updates/contrib/auth/views.py
shuyucms/boot/updates/contrib/auth/locale/zh_CN/LC_MESSAGES/django.mo
shuyucms/boot/updates/contrib/auth/locale/zh_CN/LC_MESSAGES/django.po
shuyucms/boot/updates/contrib/comments/__init__.py
shuyucms/boot/updates/contrib/comments/admin.py
shuyucms/boot/updates/contrib/comments/forms.py
shuyucms/boot/updates/contrib/comments/managers.py
shuyucms/boot/updates/contrib/comments/models.py
shuyucms/boot/updates/contrib/comments/moderation.py
shuyucms/boot/updates/contrib/comments/signals.py
shuyucms/boot/updates/contrib/comments/urls.py
shuyucms/boot/updates/contrib/comments/views/__init__.py
shuyucms/boot/updates/contrib/comments/views/comments.py
shuyucms/boot/updates/contrib/comments/views/moderation.py
shuyucms/boot/updates/contrib/comments/views/utils.py
shuyucms/conf/__init__.py
shuyucms/conf/admin.py
shuyucms/conf/context_processors.py
shuyucms/conf/forms.py
shuyucms/conf/models.py
shuyucms/conf/tests.py
shuyucms/conf/locale/en/LC_MESSAGES/django.mo
shuyucms/conf/locale/en/LC_MESSAGES/django.po
shuyucms/conf/locale/zh_CN/LC_MESSAGES/django.mo
shuyucms/conf/locale/zh_CN/LC_MESSAGES/django.po
